{
	"class" : {
		"checkError:" : "tobe 7/9/2020 16:14",
		"example" : "tobe 7/11/2020 19:05",
		"ftLoadForceAutohint" : "tobe 7/11/2020 19:10",
		"ftLoadRender" : "tobe 7/11/2020 19:03",
		"ftLoadTargetLCD" : "tobe 7/11/2020 19:05",
		"ftLoadTargetLight" : "tobe 7/11/2020 19:08",
		"glyphFormatBitmap" : "tobe 7/10/2020 09:42",
		"glyphFormatComposite" : "tobe 7/10/2020 09:42",
		"glyphFormatNone" : "tobe 7/10/2020 09:42",
		"glyphFormatOutline" : "tobe 7/10/2020 09:43",
		"glyphFormatPlotter" : "tobe 7/10/2020 09:43",
		"moduleName" : "tobe 7/9/2020 14:31" },
	"instance" : {
		"ftDoneGlyph:" : "tobe 7/13/2020 08:26",
		"ftGetCharIndex:with:" : "tobe 7/10/2020 07:39",
		"ftGetGlyph:with:" : "tobe 7/9/2020 16:08",
		"ftGlyphToBitmap:with:with:with:" : "tobe 7/10/2020 07:43",
		"ftInitFreeType:" : "tobe 7/9/2020 14:49",
		"ftLibrarySetLcdFilter:with:" : "tobe 7/10/2020 20:18",
		"ftLoadChar:with:with:" : "tobe 7/11/2020 19:02",
		"ftLoadGlyph:with:with:" : "tobe 7/9/2020 15:19",
		"ftNewFace:with:with:with:" : "tobe 7/9/2020 15:36",
		"ftSetCharSize:with:with:with:with:" : "tobe 7/11/2020 11:15",
		"ftSetPixelSizes:with:with:" : "tobe 7/9/2020 15:37" } }
